simple_poller/__init__.py
simple_poller/base_poller.py
simple_poller/sqs_poller.py
simple_poller-0.1.5.dist-info/METADATA
simple_poller-0.1.5.dist-info/WHEEL
simple_poller-0.1.5.dist-info/licenses/LICENSE
simple_poller-0.1.5.dist-info/RECORD
